{
  "meta": {
    "generated_at": "2025-10-26T16:31:47.579Z",
    "url": "balderton.com",
    "country": "United Kingdom",
    "industry": "Finance"
  },
  "latest_scores": {
    "performance": 54,
    "accessibility": 83,
    "best_practices": 92,
    "seo": 86,
    "pwa": 33,
    "test_date": "2025-10-26 13:43:19"
  },
  "historical_data": [
    {
      "performance": 54,
      "accessibility": 83,
      "best_practices": 92,
      "seo": 86,
      "pwa": 33,
      "test_date": "2025-10-26 13:43:19"
    },
    {
      "performance": 52,
      "accessibility": 83,
      "best_practices": 92,
      "seo": 86,
      "pwa": 33,
      "test_date": "2025-10-26 13:23:52"
    },
    {
      "performance": 58,
      "accessibility": 83,
      "best_practices": 92,
      "seo": 86,
      "pwa": 33,
      "test_date": "2025-10-26 12:46:11"
    },
    {
      "performance": 52,
      "accessibility": 83,
      "best_practices": 92,
      "seo": 86,
      "pwa": 33,
      "test_date": "2025-10-26 12:21:19"
    }
  ],
  "trends": {
    "performance": 2,
    "accessibility": 0,
    "best_practices": 0,
    "seo": 0,
    "pwa": 0,
    "test_date_current": "2025-10-26 13:43:19",
    "test_date_previous": "2025-10-26 13:23:52"
  }
}