{
  "meta": {
    "generated_at": "2025-11-04T09:33:30.235Z",
    "url": "fortum.se",
    "country": "Sweden",
    "industry": "Energy"
  },
  "latest_scores": {
    "performance": 28,
    "accessibility": 91,
    "best_practices": 83,
    "seo": 86,
    "pwa": 33,
    "test_date": "2025-11-04 00:43:00"
  },
  "historical_data": [
    {
      "performance": 28,
      "accessibility": 91,
      "best_practices": 83,
      "seo": 86,
      "pwa": 33,
      "test_date": "2025-11-04 00:43:00"
    }
  ],
  "trends": null
}