{
  "meta": {
    "generated_at": "2025-11-04T09:33:29.997Z",
    "url": "globo.com",
    "country": "Brazil",
    "industry": "Media"
  },
  "latest_scores": {
    "performance": 26,
    "accessibility": 85,
    "best_practices": 67,
    "seo": 99,
    "pwa": 78,
    "test_date": "2025-11-04 03:23:19"
  },
  "historical_data": [
    {
      "performance": 26,
      "accessibility": 85,
      "best_practices": 67,
      "seo": 99,
      "pwa": 78,
      "test_date": "2025-11-04 03:23:19"
    },
    {
      "performance": 56,
      "accessibility": 82,
      "best_practices": 83,
      "seo": 93,
      "pwa": 67,
      "test_date": "2025-10-19 19:50:49"
    }
  ],
  "trends": {
    "performance": -30,
    "accessibility": 3,
    "best_practices": -16,
    "seo": 6,
    "pwa": 11,
    "test_date_current": "2025-11-04 03:23:19",
    "test_date_previous": "2025-10-19 19:50:49"
  }
}