{
  "meta": {
    "generated_at": "2025-11-14T08:57:18.125Z",
    "url": "ing.pl",
    "country": "Poland",
    "industry": "Finance"
  },
  "latest_scores": {
    "performance": 0,
    "accessibility": 69,
    "best_practices": 75,
    "seo": 67,
    "pwa": 33,
    "test_date": "2025-11-11 16:20:57"
  },
  "historical_data": [
    {
      "performance": 0,
      "accessibility": 69,
      "best_practices": 75,
      "seo": 67,
      "pwa": 33,
      "test_date": "2025-11-11 16:20:57"
    },
    {
      "performance": 0,
      "accessibility": 69,
      "best_practices": 75,
      "seo": 67,
      "pwa": 33,
      "test_date": "2025-11-04 16:21:48"
    },
    {
      "performance": 56,
      "accessibility": 89,
      "best_practices": 92,
      "seo": 99,
      "pwa": 44,
      "test_date": "2025-10-28 18:20:17"
    }
  ],
  "trends": {
    "performance": 0,
    "accessibility": 0,
    "best_practices": 0,
    "seo": 0,
    "pwa": 0,
    "test_date_current": "2025-11-11 16:20:57",
    "test_date_previous": "2025-11-04 16:21:48"
  }
}