{
  "meta": {
    "generated_at": "2025-11-14T08:57:18.026Z",
    "url": "jnu.ac.in",
    "country": "India",
    "industry": "Education"
  },
  "latest_scores": {
    "performance": 55,
    "accessibility": 74,
    "best_practices": 83,
    "seo": 79,
    "pwa": 33,
    "test_date": "2025-11-11 20:12:58"
  },
  "historical_data": [
    {
      "performance": 55,
      "accessibility": 74,
      "best_practices": 83,
      "seo": 79,
      "pwa": 33,
      "test_date": "2025-11-11 20:12:58"
    },
    {
      "performance": 55,
      "accessibility": 74,
      "best_practices": 83,
      "seo": 79,
      "pwa": 33,
      "test_date": "2025-11-04 20:13:07"
    },
    {
      "performance": 37,
      "accessibility": 74,
      "best_practices": 83,
      "seo": 79,
      "pwa": 33,
      "test_date": "2025-10-28 22:10:50"
    }
  ],
  "trends": {
    "performance": 0,
    "accessibility": 0,
    "best_practices": 0,
    "seo": 0,
    "pwa": 0,
    "test_date_current": "2025-11-11 20:12:58",
    "test_date_previous": "2025-11-04 20:13:07"
  }
}