{
  "meta": {
    "generated_at": "2025-11-04T11:35:47.620Z",
    "url": "kenyans.co.ke",
    "country": "Kenya",
    "industry": "Media"
  },
  "latest_scores": {
    "performance": 45,
    "accessibility": 98,
    "best_practices": 75,
    "seo": 93,
    "pwa": 33,
    "test_date": "2025-10-29 00:46:24"
  },
  "historical_data": [
    {
      "performance": 45,
      "accessibility": 98,
      "best_practices": 75,
      "seo": 93,
      "pwa": 33,
      "test_date": "2025-10-29 00:46:24"
    },
    {
      "performance": 50,
      "accessibility": 98,
      "best_practices": 67,
      "seo": 93,
      "pwa": 33,
      "test_date": "2025-10-21 20:19:07"
    },
    {
      "performance": 47,
      "accessibility": 98,
      "best_practices": 75,
      "seo": 93,
      "pwa": 33,
      "test_date": "2025-10-21 17:15:12"
    },
    {
      "performance": 47,
      "accessibility": 98,
      "best_practices": 75,
      "seo": 93,
      "pwa": 33,
      "test_date": "2025-10-21 16:47:42"
    },
    {
      "performance": 34,
      "accessibility": 98,
      "best_practices": 75,
      "seo": 93,
      "pwa": 33,
      "test_date": "2025-10-21 16:20:41"
    }
  ],
  "trends": {
    "performance": -5,
    "accessibility": 0,
    "best_practices": 8,
    "seo": 0,
    "pwa": 0,
    "test_date_current": "2025-10-29 00:46:24",
    "test_date_previous": "2025-10-21 20:19:07"
  }
}