{
  "meta": {
    "generated_at": "2025-11-14T08:39:15.086Z",
    "url": "letemps.ch",
    "country": "Switzerland",
    "industry": "Media"
  },
  "latest_scores": {
    "performance": 35,
    "accessibility": 100,
    "best_practices": 83,
    "seo": 100,
    "pwa": 89,
    "test_date": "2025-11-12 04:20:41"
  },
  "historical_data": [
    {
      "performance": 35,
      "accessibility": 100,
      "best_practices": 83,
      "seo": 100,
      "pwa": 89,
      "test_date": "2025-11-12 04:20:41"
    },
    {
      "performance": 34,
      "accessibility": 100,
      "best_practices": 92,
      "seo": 100,
      "pwa": 89,
      "test_date": "2025-11-05 04:17:50"
    },
    {
      "performance": 37,
      "accessibility": 100,
      "best_practices": 83,
      "seo": 100,
      "pwa": 89,
      "test_date": "2025-10-29 07:47:54"
    },
    {
      "performance": 38,
      "accessibility": 100,
      "best_practices": 83,
      "seo": 100,
      "pwa": 89,
      "test_date": "2025-10-29 06:20:39"
    },
    {
      "performance": 34,
      "accessibility": 100,
      "best_practices": 92,
      "seo": 100,
      "pwa": 89,
      "test_date": "2025-10-22 03:10:08"
    }
  ],
  "trends": {
    "performance": 1,
    "accessibility": 0,
    "best_practices": -9,
    "seo": 0,
    "pwa": 0,
    "test_date_current": "2025-11-12 04:20:41",
    "test_date_previous": "2025-11-05 04:17:50"
  }
}