{
  "meta": {
    "generated_at": "2025-11-04T09:57:35.198Z",
    "url": "rtbf.be",
    "country": "Belgium",
    "industry": "Media"
  },
  "latest_scores": {
    "performance": 41,
    "accessibility": 96,
    "best_practices": 92,
    "seo": 100,
    "pwa": 33,
    "test_date": "2025-10-30 22:09:24"
  },
  "historical_data": [
    {
      "performance": 41,
      "accessibility": 96,
      "best_practices": 92,
      "seo": 100,
      "pwa": 33,
      "test_date": "2025-10-30 22:09:24"
    },
    {
      "performance": 36,
      "accessibility": 97,
      "best_practices": 83,
      "seo": 99,
      "pwa": 33,
      "test_date": "2025-10-23 15:56:22"
    },
    {
      "performance": 34,
      "accessibility": 98,
      "best_practices": 83,
      "seo": 100,
      "pwa": 33,
      "test_date": "2025-10-23 14:22:53"
    }
  ],
  "trends": {
    "performance": 5,
    "accessibility": -1,
    "best_practices": 9,
    "seo": 1,
    "pwa": 0,
    "test_date_current": "2025-10-30 22:09:24",
    "test_date_previous": "2025-10-23 15:56:22"
  }
}