{
  "meta": {
    "generated_at": "2025-11-04T09:04:16.777Z",
    "url": "rts.ch",
    "country": "Switzerland",
    "industry": "Media"
  },
  "latest_scores": {
    "performance": 54,
    "accessibility": 92,
    "best_practices": 75,
    "seo": 93,
    "pwa": 33,
    "test_date": "2025-10-30 22:11:28"
  },
  "historical_data": [
    {
      "performance": 54,
      "accessibility": 92,
      "best_practices": 75,
      "seo": 93,
      "pwa": 33,
      "test_date": "2025-10-30 22:11:28"
    },
    {
      "performance": 56,
      "accessibility": 99,
      "best_practices": 83,
      "seo": 100,
      "pwa": 33,
      "test_date": "2025-10-23 16:43:05"
    },
    {
      "performance": 56,
      "accessibility": 99,
      "best_practices": 83,
      "seo": 100,
      "pwa": 33,
      "test_date": "2025-10-23 16:12:08"
    }
  ],
  "trends": {
    "performance": -2,
    "accessibility": -7,
    "best_practices": -8,
    "seo": -7,
    "pwa": 0,
    "test_date_current": "2025-10-30 22:11:28",
    "test_date_previous": "2025-10-23 16:43:05"
  }
}