{
  "meta": {
    "generated_at": "2025-11-04T12:50:44.894Z",
    "url": "stc.com.sa",
    "country": "Saudi Arabia",
    "industry": "Telecom"
  },
  "latest_scores": {
    "performance": 25,
    "accessibility": 73,
    "best_practices": 83,
    "seo": 86,
    "pwa": 89,
    "test_date": "2025-10-31 10:11:35"
  },
  "historical_data": [
    {
      "performance": 25,
      "accessibility": 73,
      "best_practices": 83,
      "seo": 86,
      "pwa": 89,
      "test_date": "2025-10-31 10:11:35"
    }
  ],
  "trends": null
}