{
  "meta": {
    "generated_at": "2025-10-26T08:29:03.046Z",
    "url": "tasnimnews.com",
    "country": "Iran",
    "industry": "Media"
  },
  "latest_scores": {
    "performance": 57,
    "accessibility": 62,
    "best_practices": 92,
    "seo": 93,
    "pwa": 33,
    "test_date": "2025-10-24 08:13:36"
  },
  "historical_data": [
    {
      "performance": 57,
      "accessibility": 62,
      "best_practices": 92,
      "seo": 93,
      "pwa": 33,
      "test_date": "2025-10-24 08:13:36"
    }
  ],
  "trends": null
}