{
  "meta": {
    "generated_at": "2025-10-28T20:19:56.558Z",
    "url": "themarker.com",
    "country": "Israel",
    "industry": "Media"
  },
  "latest_scores": {
    "performance": 34,
    "accessibility": 88,
    "best_practices": 83,
    "seo": 99,
    "pwa": 44,
    "test_date": "2025-10-19 20:21:59"
  },
  "historical_data": [
    {
      "performance": 34,
      "accessibility": 88,
      "best_practices": 83,
      "seo": 99,
      "pwa": 44,
      "test_date": "2025-10-19 20:21:59"
    }
  ],
  "trends": null
}