{
  "meta": {
    "generated_at": "2025-10-26T16:21:14.517Z",
    "country": "Germany",
    "flag": "🇩🇪",
    "website_count": 22
  },
  "averages": {
    "performance": 42,
    "accessibility": 88,
    "best_practices": 88,
    "seo": 93,
    "pwa": 51
  },
  "websites": [
    {
      "url": "web.de",
      "industry": "Portal",
      "scores": {
        "performance": 88,
        "accessibility": 100,
        "best_practices": 75,
        "seo": 85,
        "pwa": 33
      },
      "test_date": "2025-10-25 03:03:39"
    },
    {
      "url": "gmx.net",
      "industry": "Portal",
      "scores": {
        "performance": 75,
        "accessibility": 100,
        "best_practices": 75,
        "seo": 85,
        "pwa": 33
      },
      "test_date": "2025-10-19 19:44:15"
    },
    {
      "url": "arbeitsagentur.de",
      "industry": "Government",
      "scores": {
        "performance": 58,
        "accessibility": 100,
        "best_practices": 100,
        "seo": 86,
        "pwa": 56
      },
      "test_date": "2025-10-26 10:10:47"
    },
    {
      "url": "heise.de",
      "industry": "Media",
      "scores": {
        "performance": 56,
        "accessibility": 83,
        "best_practices": 92,
        "seo": 93,
        "pwa": 56
      },
      "test_date": "2025-10-19 19:44:00"
    },
    {
      "url": "chip.de",
      "industry": "Media",
      "scores": {
        "performance": 48,
        "accessibility": 91,
        "best_practices": 92,
        "seo": 93,
        "pwa": 56
      },
      "test_date": "2025-10-19 19:43:17"
    },
    {
      "url": "focus.de",
      "industry": "Media",
      "scores": {
        "performance": 48,
        "accessibility": 88,
        "best_practices": 100,
        "seo": 100,
        "pwa": 89
      },
      "test_date": "2025-10-20 20:11:07"
    },
    {
      "url": "bmw.de",
      "industry": "Automotive",
      "scores": {
        "performance": 46,
        "accessibility": 100,
        "best_practices": 83,
        "seo": 100,
        "pwa": 33
      },
      "test_date": "2025-10-22 08:31:37"
    },
    {
      "url": "tagesschau.de",
      "industry": "Media",
      "scores": {
        "performance": 46,
        "accessibility": 88,
        "best_practices": 83,
        "seo": 93,
        "pwa": 33
      },
      "test_date": "2025-10-24 06:18:01"
    },
    {
      "url": "spiegel.de",
      "industry": "Media",
      "scores": {
        "performance": 45,
        "accessibility": 98,
        "best_practices": 100,
        "seo": 93,
        "pwa": 78
      },
      "test_date": "2025-10-24 00:40:36"
    },
    {
      "url": "welt.de",
      "industry": "Media",
      "scores": {
        "performance": 41,
        "accessibility": 92,
        "best_practices": 83,
        "seo": 100,
        "pwa": 33
      },
      "test_date": "2025-10-25 04:11:51"
    },
    {
      "url": "bild.de",
      "industry": "Media",
      "scores": {
        "performance": 40,
        "accessibility": 96,
        "best_practices": 92,
        "seo": 100,
        "pwa": 44
      },
      "test_date": "2025-10-19 19:41:29"
    },
    {
      "url": "sparkasse.de",
      "industry": "Finance",
      "scores": {
        "performance": 40,
        "accessibility": 92,
        "best_practices": 92,
        "seo": 100,
        "pwa": 56
      },
      "test_date": "2025-10-24 00:40:09"
    },
    {
      "url": "saturn.de",
      "industry": "E-commerce",
      "scores": {
        "performance": 39,
        "accessibility": 90,
        "best_practices": 92,
        "seo": 97,
        "pwa": 78
      },
      "test_date": "2025-10-23 19:31:29"
    },
    {
      "url": "volkswagen.de",
      "industry": "Automotive",
      "scores": {
        "performance": 39,
        "accessibility": 97,
        "best_practices": 83,
        "seo": 95,
        "pwa": 33
      },
      "test_date": "2025-10-25 00:51:27"
    },
    {
      "url": "zeit.de",
      "industry": "Media",
      "scores": {
        "performance": 39,
        "accessibility": 86,
        "best_practices": 92,
        "seo": 86,
        "pwa": 78
      },
      "test_date": "2025-10-25 10:16:16"
    },
    {
      "url": "t-online.de",
      "industry": "Portal",
      "scores": {
        "performance": 35,
        "accessibility": 76,
        "best_practices": 100,
        "seo": 93,
        "pwa": 89
      },
      "test_date": "2025-10-24 06:15:06"
    },
    {
      "url": "zalando.de",
      "industry": "E-commerce",
      "scores": {
        "performance": 30,
        "accessibility": 0,
        "best_practices": 75,
        "seo": 100,
        "pwa": 22
      },
      "test_date": "2025-10-25 10:08:45"
    },
    {
      "url": "bahn.de",
      "industry": "Transportation",
      "scores": {
        "performance": 30,
        "accessibility": 82,
        "best_practices": 92,
        "seo": 91,
        "pwa": 33
      },
      "test_date": "2025-10-26 13:42:30"
    },
    {
      "url": "sueddeutsche.de",
      "industry": "Media",
      "scores": {
        "performance": 28,
        "accessibility": 91,
        "best_practices": 100,
        "seo": 93,
        "pwa": 56
      },
      "test_date": "2025-10-24 04:11:39"
    },
    {
      "url": "otto.de",
      "industry": "E-commerce",
      "scores": {
        "performance": 25,
        "accessibility": 91,
        "best_practices": 75,
        "seo": 85,
        "pwa": 67
      },
      "test_date": "2025-10-23 03:01:46"
    },
    {
      "url": "postbank.de",
      "industry": "Finance",
      "scores": {
        "performance": 17,
        "accessibility": 85,
        "best_practices": 83,
        "seo": 86,
        "pwa": 33
      },
      "test_date": "2025-10-23 08:29:50"
    },
    {
      "url": "mercedes-benz.de",
      "industry": "Automotive",
      "scores": {
        "performance": 7,
        "accessibility": 100,
        "best_practices": 83,
        "seo": 100,
        "pwa": 33
      },
      "test_date": "2025-10-22 12:20:09"
    }
  ],
  "industries": [
    {
      "industry": "Automotive",
      "website_count": 3,
      "averages": {
        "performance": 31,
        "accessibility": 99,
        "best_practices": 83,
        "seo": 98,
        "pwa": 33
      }
    },
    {
      "industry": "E-commerce",
      "website_count": 3,
      "averages": {
        "performance": 31,
        "accessibility": 60,
        "best_practices": 81,
        "seo": 94,
        "pwa": 56
      }
    },
    {
      "industry": "Finance",
      "website_count": 2,
      "averages": {
        "performance": 29,
        "accessibility": 89,
        "best_practices": 88,
        "seo": 93,
        "pwa": 45
      }
    },
    {
      "industry": "Government",
      "website_count": 1,
      "averages": {
        "performance": 58,
        "accessibility": 100,
        "best_practices": 100,
        "seo": 86,
        "pwa": 56
      }
    },
    {
      "industry": "Media",
      "website_count": 9,
      "averages": {
        "performance": 43,
        "accessibility": 90,
        "best_practices": 93,
        "seo": 95,
        "pwa": 58
      }
    },
    {
      "industry": "Portal",
      "website_count": 3,
      "averages": {
        "performance": 66,
        "accessibility": 92,
        "best_practices": 83,
        "seo": 88,
        "pwa": 52
      }
    },
    {
      "industry": "Transportation",
      "website_count": 1,
      "averages": {
        "performance": 30,
        "accessibility": 82,
        "best_practices": 92,
        "seo": 91,
        "pwa": 33
      }
    }
  ]
}