{
  "meta": {
    "generated_at": "2025-11-14T08:39:13.558Z",
    "country": "Hong Kong",
    "flag": "🌍",
    "website_count": 8
  },
  "averages": {
    "performance": 28,
    "accessibility": 78,
    "best_practices": 75,
    "seo": 84,
    "pwa": 37
  },
  "websites": [
    {
      "url": "hkt.com",
      "industry": "Telecom",
      "scores": {
        "performance": 61,
        "accessibility": 86,
        "best_practices": 83,
        "seo": 90,
        "pwa": 22
      },
      "test_date": "2025-11-11 08:27:24"
    },
    {
      "url": "pccw.com",
      "industry": "Telecom",
      "scores": {
        "performance": 46,
        "accessibility": 84,
        "best_practices": 100,
        "seo": 82,
        "pwa": 33
      },
      "test_date": "2025-11-13 10:13:20"
    },
    {
      "url": "rthk.hk",
      "industry": "Media",
      "scores": {
        "performance": 36,
        "accessibility": 60,
        "best_practices": 67,
        "seo": 77,
        "pwa": 33
      },
      "test_date": "2025-11-13 22:11:36"
    },
    {
      "url": "hket.com",
      "industry": "Media",
      "scores": {
        "performance": 33,
        "accessibility": 86,
        "best_practices": 67,
        "seo": 91,
        "pwa": 33
      },
      "test_date": "2025-11-11 08:27:05"
    },
    {
      "url": "cathaypacific.com",
      "industry": "Transportation",
      "scores": {
        "performance": 25,
        "accessibility": 55,
        "best_practices": 83,
        "seo": 79,
        "pwa": 44
      },
      "test_date": "2025-11-09 20:19:25"
    },
    {
      "url": "hsbc.com.hk",
      "industry": "Finance",
      "scores": {
        "performance": 11,
        "accessibility": 90,
        "best_practices": 67,
        "seo": 93,
        "pwa": 67
      },
      "test_date": "2025-11-11 10:18:42"
    },
    {
      "url": "hangseng.com",
      "industry": "Finance",
      "scores": {
        "performance": 8,
        "accessibility": 87,
        "best_practices": 67,
        "seo": 85,
        "pwa": 33
      },
      "test_date": "2025-11-11 06:31:05"
    },
    {
      "url": "mtr.com.hk",
      "industry": "Transportation",
      "scores": {
        "performance": 7,
        "accessibility": 78,
        "best_practices": 67,
        "seo": 74,
        "pwa": 33
      },
      "test_date": "2025-11-12 18:17:25"
    }
  ],
  "industries": [
    {
      "industry": "Finance",
      "website_count": 2,
      "averages": {
        "performance": 10,
        "accessibility": 89,
        "best_practices": 67,
        "seo": 89,
        "pwa": 50
      }
    },
    {
      "industry": "Media",
      "website_count": 2,
      "averages": {
        "performance": 35,
        "accessibility": 73,
        "best_practices": 67,
        "seo": 84,
        "pwa": 33
      }
    },
    {
      "industry": "Telecom",
      "website_count": 2,
      "averages": {
        "performance": 54,
        "accessibility": 85,
        "best_practices": 92,
        "seo": 86,
        "pwa": 28
      }
    },
    {
      "industry": "Transportation",
      "website_count": 2,
      "averages": {
        "performance": 16,
        "accessibility": 67,
        "best_practices": 75,
        "seo": 77,
        "pwa": 39
      }
    }
  ]
}