{
  "meta": {
    "generated_at": "2025-10-26T13:10:43.362Z",
    "industry": "Sports",
    "website_count": 7
  },
  "averages": {
    "performance": 44,
    "accessibility": 80,
    "best_practices": 80,
    "seo": 86,
    "pwa": 40
  },
  "websites": [
    {
      "url": "hockeycanada.ca",
      "country": "Canada",
      "scores": {
        "performance": 60,
        "accessibility": 77,
        "best_practices": 83,
        "seo": 76,
        "pwa": 22
      },
      "test_date": "2025-10-19 20:00:05"
    },
    {
      "url": "yallakora.com",
      "country": "Egypt",
      "scores": {
        "performance": 34,
        "accessibility": 96,
        "best_practices": 67,
        "seo": 91,
        "pwa": 67
      },
      "test_date": "2025-10-25 08:11:24"
    },
    {
      "url": "cricbuzz.com",
      "country": "India",
      "scores": {
        "performance": 72,
        "accessibility": 84,
        "best_practices": 92,
        "seo": 99,
        "pwa": 33
      },
      "test_date": "2025-10-19 19:46:43"
    },
    {
      "url": "sport5.co.il",
      "country": "Israel",
      "scores": {
        "performance": 28,
        "accessibility": 61,
        "best_practices": 58,
        "seo": 70,
        "pwa": 33
      },
      "test_date": "2025-10-19 20:22:17"
    },
    {
      "url": "sport.sk",
      "country": "Slovakia",
      "scores": {
        "performance": 37,
        "accessibility": 68,
        "best_practices": 75,
        "seo": 83,
        "pwa": 33
      },
      "test_date": "2025-10-24 00:41:06"
    },
    {
      "url": "marca.com",
      "country": "Spain",
      "scores": {
        "performance": 28,
        "accessibility": 96,
        "best_practices": 92,
        "seo": 90,
        "pwa": 33
      },
      "test_date": "2025-10-22 10:11:29"
    },
    {
      "url": "sport.ua",
      "country": "Ukraine",
      "scores": {
        "performance": 50,
        "accessibility": 78,
        "best_practices": 92,
        "seo": 92,
        "pwa": 56
      },
      "test_date": "2025-10-24 00:41:27"
    }
  ],
  "countries": [
    {
      "country": "Canada",
      "website_count": 1,
      "averages": {
        "performance": 60,
        "accessibility": 77,
        "best_practices": 83,
        "seo": 76,
        "pwa": 22
      }
    },
    {
      "country": "Egypt",
      "website_count": 1,
      "averages": {
        "performance": 34,
        "accessibility": 96,
        "best_practices": 67,
        "seo": 91,
        "pwa": 67
      }
    },
    {
      "country": "India",
      "website_count": 1,
      "averages": {
        "performance": 72,
        "accessibility": 84,
        "best_practices": 92,
        "seo": 99,
        "pwa": 33
      }
    },
    {
      "country": "Israel",
      "website_count": 1,
      "averages": {
        "performance": 28,
        "accessibility": 61,
        "best_practices": 58,
        "seo": 70,
        "pwa": 33
      }
    },
    {
      "country": "Slovakia",
      "website_count": 1,
      "averages": {
        "performance": 37,
        "accessibility": 68,
        "best_practices": 75,
        "seo": 83,
        "pwa": 33
      }
    },
    {
      "country": "Spain",
      "website_count": 1,
      "averages": {
        "performance": 28,
        "accessibility": 96,
        "best_practices": 92,
        "seo": 90,
        "pwa": 33
      }
    },
    {
      "country": "Ukraine",
      "website_count": 1,
      "averages": {
        "performance": 50,
        "accessibility": 78,
        "best_practices": 92,
        "seo": 92,
        "pwa": 56
      }
    }
  ]
}